Products.ExternalEditor-4.0.1-py3.11-nspkg.pth
Products/ExternalEditor/ExternalEditor.py
Products/ExternalEditor/LICENSE.txt
Products/ExternalEditor/__init__.py
Products/ExternalEditor/client.txt
Products/ExternalEditor/edit_icon.gif
Products/ExternalEditor/findResult.dtml
Products/ExternalEditor/dtml/findForm.dtml
Products/ExternalEditor/tests/__init__.py
Products/ExternalEditor/tests/edit.txt
Products/ExternalEditor/tests/link.txt
Products/ExternalEditor/tests/test_PDataStreamIterator.py
Products/ExternalEditor/tests/test_functional.py
Products/ExternalEditor/tests/test_zmi.py
Products/ExternalEditor/zpt/main.zpt
Products.ExternalEditor-4.0.1.dist-info/LICENSE.txt
Products.ExternalEditor-4.0.1.dist-info/METADATA
Products.ExternalEditor-4.0.1.dist-info/WHEEL
Products.ExternalEditor-4.0.1.dist-info/namespace_packages.txt
Products.ExternalEditor-4.0.1.dist-info/top_level.txt
Products.ExternalEditor-4.0.1.dist-info/RECORD
